MANIFEST.in
README.rst
setup.py
arclib/__init__.py
arclib/_rfile.py
arclib/bz2.py
arclib/gz.py
arclib/lzma.py
arclib/tar.py
arclib/zip.py
arclib.egg-info/PKG-INFO
arclib.egg-info/SOURCES.txt
arclib.egg-info/dependency_links.txt
arclib.egg-info/top_level.txt
docs/source/conf.py
docs/source/index.rst
tests/test_bz2.py
tests/test_lzma.py
tests/util.py