Metadata-Version: 1.1
Name: arclib
Version: 0.2.1
Summary: A unified API for accessing Python's compression formats
Home-page: https://github.com/kirbyfan64/arclib
Author: Ryan Gonzalez
Author-email: rymg19@gmail.com
License: UNKNOWN
Platform: UNKNOWN
Classifier: Programming Language :: Python :: 3 :: Only
Classifier: Topic :: System :: Archiving
Classifier: License :: OSI Approved :: MIT License
